{"cameraMode":{"drawMode":0,"name":"Shaded","section":"Shading Mode"},"sceneLighting":true,"audioPlay":false,"sceneViewState":{"m_AlwaysRefresh":false,"showFog":true,"showSkybox":true,"showFlares":true,"showImageEffects":true,"showParticleSystems":true,"showVisualEffectGraphs":true,"m_FxEnabled":true},"in2DMode":false,"pivot":{"x":5.251858711242676,"y":68.48636627197266,"z":-6.158820152282715},"rotation":{"x":-0.04506676271557808,"y":-0.9246103763580322,"z":-0.11571254581212998,"w":0.36011070013046267},"size":129.09967041015626,"orthographic":false}